pyexcelios/.constants.json
pyexcelios/__init__.py
pyexcelios/conftest.py
pyexcelios/benchmarks/__init__.py
pyexcelios/benchmarks/bufzip.py
pyexcelios/benchmarks/memory.py
pyexcelios/benchmarks/profiling.py
pyexcelios/benchmarks/reader.py
pyexcelios/benchmarks/speed.py
pyexcelios/benchmarks/writer.py
pyexcelios/cell/__init__.py
pyexcelios/cell/cell.py
pyexcelios/cell/interface.py
pyexcelios/cell/read_only.py
pyexcelios/cell/text.py
pyexcelios/cell/tests/__init__.py
pyexcelios/cell/tests/test_cell.py
pyexcelios/cell/tests/test_read_only.py
pyexcelios/cell/tests/test_text.py
pyexcelios/chart/_3d.py
pyexcelios/chart/__init__.py
pyexcelios/chart/_chart.py
pyexcelios/chart/area_chart.py
pyexcelios/chart/axis.py
pyexcelios/chart/bar_chart.py
pyexcelios/chart/bubble_chart.py
pyexcelios/chart/chartspace.py
pyexcelios/chart/data_source.py
pyexcelios/chart/descriptors.py
pyexcelios/chart/error_bar.py
pyexcelios/chart/label.py
pyexcelios/chart/layout.py
pyexcelios/chart/legend.py
pyexcelios/chart/line_chart.py
pyexcelios/chart/marker.py
pyexcelios/chart/picture.py
pyexcelios/chart/pie_chart.py
pyexcelios/chart/radar_chart.py
pyexcelios/chart/reference.py
pyexcelios/chart/scatter_chart.py
pyexcelios/chart/series.py
pyexcelios/chart/series_factory.py
pyexcelios/chart/shapes.py
pyexcelios/chart/stock_chart.py
pyexcelios/chart/surface_chart.py
pyexcelios/chart/text.py
pyexcelios/chart/title.py
pyexcelios/chart/trendline.py
pyexcelios/chart/updown_bars.py
pyexcelios/chart/tests/__init__.py
pyexcelios/chart/tests/test_area_chart.py
pyexcelios/chart/tests/test_axis.py
pyexcelios/chart/tests/test_bar_chart.py
pyexcelios/chart/tests/test_bubble_chart.py
pyexcelios/chart/tests/test_chart.py
pyexcelios/chart/tests/test_chartspace.py
pyexcelios/chart/tests/test_data_source.py
pyexcelios/chart/tests/test_error_bar.py
pyexcelios/chart/tests/test_label.py
pyexcelios/chart/tests/test_layout.py
pyexcelios/chart/tests/test_legend.py
pyexcelios-2.3.5.dist-info/DESCRIPTION.rst
pyexcelios-2.3.5.dist-info/METADATA
pyexcelios-2.3.5.dist-info/RECORD
pyexcelios-2.3.5.dist-info/WHEEL
pyexcelios-2.3.5.dist-info/metadata.json
pyexcelios-2.3.5.dist-info/top_level.txt
