Metadata-Version: 2.0
Name: pyexcelios
Version: 2.3.5
Summary: A Python library to read/write Excel 2010 xlsx/xlsm files
Home-page: http://openpyxl.readthedocs.org
Author: See AUTHORS
Author-email: eric.gazoni@gmail.com
License: MIT/Expat
Platform: UNKNOWN
Classifier: Development Status :: 5 - Production/Stable
Classifier: Operating System :: MacOS :: MacOS X
Classifier: Operating System :: Microsoft :: Windows
Classifier: Operating System :: POSIX
Classifier: License :: OSI Approved :: MIT License
Classifier: Programming Language :: Python
Classifier: Programming Language :: Python :: 2.6
Classifier: Programming Language :: Python :: 2.7
Classifier: Programming Language :: Python :: 3.3
Classifier: Programming Language :: Python :: 3.4
Requires: python (>=2.6.0)
Requires-Dist: et-xmlfile
Requires-Dist: jdcal
